autojmp/__init__.py
autojmp-0.3.0.dist-info/licenses/LICENSE
autojmp-0.3.0.dist-info/METADATA
autojmp-0.3.0.dist-info/WHEEL
autojmp-0.3.0.dist-info/entry_points.txt
autojmp-0.3.0.dist-info/top_level.txt
autojmp-0.3.0.dist-info/RECORD
